CHANGELOG.txt
LICENSE.txt
MANIFEST.in
README.txt
setup.cfg
setup.py
buildkit/__init__.py
buildkit/conf.py
buildkit/localstacks.py
buildkit/run.py
buildkit-apt-cache_deb/DEBIAN/changelog
buildkit-apt-cache_deb/DEBIAN/compat
buildkit-apt-cache_deb/DEBIAN/control
buildkit-apt-cache_deb/DEBIAN/control.template
buildkit-apt-cache_deb/DEBIAN/copyright
buildkit-apt-cache_deb/DEBIAN/docs
buildkit-apt-cache_deb/DEBIAN/postinst
buildkit-apt-cache_deb/DEBIAN/rules
buildkit-apt-repo_deb/DEBIAN/changelog
buildkit-apt-repo_deb/DEBIAN/compat
buildkit-apt-repo_deb/DEBIAN/control
buildkit-apt-repo_deb/DEBIAN/control.template
buildkit-apt-repo_deb/DEBIAN/copyright
buildkit-apt-repo_deb/DEBIAN/docs
buildkit-apt-repo_deb/DEBIAN/postinst
buildkit-apt-repo_deb/DEBIAN/rules
buildkit-deb_deb/DEBIAN/changelog
buildkit-deb_deb/DEBIAN/compat
buildkit-deb_deb/DEBIAN/control
buildkit-deb_deb/DEBIAN/control.template
buildkit-deb_deb/DEBIAN/copyright
buildkit-deb_deb/DEBIAN/docs
buildkit-deb_deb/DEBIAN/postinst
buildkit-deb_deb/DEBIAN/rules
buildkit-deb_deb/usr/bin/buildkit-gitflow-installer
buildkit-vm_deb/DEBIAN/changelog
buildkit-vm_deb/DEBIAN/compat
buildkit-vm_deb/DEBIAN/control
buildkit-vm_deb/DEBIAN/control.template
buildkit-vm_deb/DEBIAN/copyright
buildkit-vm_deb/DEBIAN/docs
buildkit-vm_deb/DEBIAN/postinst
buildkit-vm_deb/DEBIAN/rules
buildkit-vm_deb/etc/supervisor/conf.d/buildkit.conf
buildkit-vm_deb/usr/bin/buildkit-vm-start
buildkit.egg-info/PKG-INFO
buildkit.egg-info/SOURCES.txt
buildkit.egg-info/dependency_links.txt
buildkit.egg-info/entry_points.txt
buildkit.egg-info/not-zip-safe
buildkit.egg-info/requires.txt
buildkit.egg-info/top_level.txt
buildkit/command/__init__.py
buildkit/command/generate.py
buildkit/command/release.py
buildkit/command/start.py
buildkit/command/build/__init__.py
buildkit/command/pkg/__init__.py
buildkit/command/pkg/nonpython.py
buildkit/command/pkg/python.py
buildkit/command/repo/__init__.py
buildkit/command/repo/add.py
buildkit/command/repo/clone.py
buildkit/command/repo/exportdeb.py
buildkit/command/repo/installkey.py
buildkit/command/repo/list.py
buildkit/command/repo/remove.py
buildkit/command/vm/__init__.py
buildkit/command/vm/create.py
buildkit/facility/__init__.py
