Metadata-Version: 1.0
Name: buildkit
Version: 0.2.2
Summary: Cloud infrastructure and .deb file management software
Home-page: http://packages.python.org/buildkit
Author: James Gardner
Author-email: UNKNOWN
License: GNU AGPLv3
Platform: UNKNOWN
Classifier: Development Status :: 3 - Alpha
Classifier: License :: OSI Approved :: GNU Affero General Public License v3
Classifier: Programming Language :: Python
